mod2pip/__init__.py
mod2pip/mapping
mod2pip/mod2pip.py
mod2pip/stdlib
mod2pip-0.9.0.dist-info/licenses/AUTHORS.rst
mod2pip-0.9.0.dist-info/licenses/LICENSE
mod2pip-0.9.0.dist-info/METADATA
mod2pip-0.9.0.dist-info/WHEEL
mod2pip-0.9.0.dist-info/entry_points.txt
mod2pip-0.9.0.dist-info/top_level.txt
mod2pip-0.9.0.dist-info/RECORD
