Metadata-Version: 2.4
Name: mod2pip
Version: 0.9.0
Summary: Enhanced pip requirements.txt generator with dynamic import detection and conda support
Author-email: Raja CSP Raman <raja.csp@gmail.com>
Maintainer-email: Raja CSP Raman <raja.csp@gmail.com>
License-Expression: Apache-2.0
Project-URL: Homepage, https://github.com/kactlabs/mod2pip
Project-URL: Repository, https://github.com/kactlabs/mod2pip
Project-URL: Documentation, https://github.com/kactlabs/mod2pip
Project-URL: Bug Tracker, https://github.com/kactlabs/mod2pip/issues
Keywords: pip,requirements,imports,dependencies,conda,dynamic-imports
Classifier: Development Status :: 4 - Beta
Classifier: Intended Audience :: Developers
Classifier: Natural Language :: English
Classifier: Programming Language :: Python :: 3
Classifier: Programming Language :: Python :: 3.9
Classifier: Programming Language :: Python :: 3.10
Classifier: Programming Language :: Python :: 3.11
Classifier: Programming Language :: Python :: 3.12
Classifier: Programming Language :: Python :: 3.13
Classifier: Topic :: Software Development :: Libraries :: Python Modules
Classifier: Topic :: System :: Software Distribution
Classifier: Topic :: Utilities
Requires-Python: >=3.9
License-File: LICENSE
License-File: AUTHORS.rst
Requires-Dist: yarg>=0.1.9
Requires-Dist: docopt>=0.6.2
Requires-Dist: requests>=2.25.0
Requires-Dist: nbconvert<8.0.0,>=7.11.0; python_version < "3.13"
Requires-Dist: nbconvert>=7.16.0; python_version >= "3.13"
Requires-Dist: ipython<8.0.0,>=7.16.0; python_version == "3.9"
Requires-Dist: ipython<8.19.0,>=8.0.0; python_version >= "3.10" and python_version < "3.13"
Requires-Dist: ipython>=8.18.0; python_version >= "3.13"
Provides-Extra: dev
Requires-Dist: flake8>=6.1.0; extra == "dev"
Requires-Dist: tox>=4.11.3; extra == "dev"
Requires-Dist: coverage>=7.3.2; extra == "dev"
Dynamic: license-file
